imagecor/__init__.py
imagecor/image_processor.py
imagecor-0.1.0.dist-info/LICENSE
imagecor-0.1.0.dist-info/METADATA
imagecor-0.1.0.dist-info/WHEEL
imagecor-0.1.0.dist-info/RECORD
