Metadata-Version: 2.1
Name: imagecor
Version: 0.1.0
Summary: Image processing utilities for Markdown files
License: MIT
Author: Your Name
Author-email: your.email@example.com
Requires-Python: >=3.9,<4.0
Classifier: License :: OSI Approved :: MIT License
Classifier: Programming Language :: Python :: 3
Classifier: Programming Language :: Python :: 3.9
Classifier: Programming Language :: Python :: 3.10
Classifier: Programming Language :: Python :: 3.11
Classifier: Programming Language :: Python :: 3.12
Requires-Dist: beautifulsoup4 (>=4.12.3,<5.0.0)
Requires-Dist: markdown (>=3.7,<4.0)
Requires-Dist: pillow (>=10.4.0,<11.0.0)
Requires-Dist: requests (>=2.32.3,<3.0.0)
